{
    "nodes": [
      {
        "id": "cov_310",
        "pdb": "cov",
        "chain": "A",
        "resnum": 329,
        "aa": "GLU",
        "name": "A329_GLU",
        "bonds": 1
      },
      {
        "id": "cov_23",
        "pdb": "cov",
        "chain": "A",
        "resnum": 42,
        "aa": "GLN",
        "name": "A42_GLN",
        "bonds": 1
      },
      {
        "id": "cov_5",
        "pdb": "cov",
        "chain": "A",
        "resnum": 24,
        "aa": "GLN",
        "name": "A24_GLN",
        "bonds": 1
      },
      {
        "id": "cov_64",
        "pdb": "cov",
        "chain": "A",
        "resnum": 83,
        "aa": "TYR",
        "name": "A83_TYR",
        "bonds": 1
      },
      {
        "id": "cov_311",
        "pdb": "cov",
        "chain": "A",
        "resnum": 330,
        "aa": "ASN",
        "name": "A330_ASN",
        "bonds": 1
      },
      {
        "id": "cov_22",
        "pdb": "cov",
        "chain": "A",
        "resnum": 41,
        "aa": "TYR",
        "name": "A41_TYR",
        "bonds": 1
      },
      {
        "id": "cov_334",
        "pdb": "cov",
        "chain": "A",
        "resnum": 353,
        "aa": "LYS",
        "name": "A353_LYS",
        "bonds": 1
      },
      {
        "id": "cov_1291",
        "pdb": "cov",
        "chain": "E",
        "resnum": 426,
        "aa": "ARG",
        "name": "E426_ARG",
        "bonds": 1
      },
      {
        "id": "cov_1301",
        "pdb": "cov",
        "chain": "E",
        "resnum": 436,
        "aa": "TYR",
        "name": "E436_TYR",
        "bonds": 1
      },
      {
        "id": "cov_1351",
        "pdb": "cov",
        "chain": "E",
        "resnum": 486,
        "aa": "THR",
        "name": "E486_THR",
        "bonds": 1
      },
      {
        "id": "cov_1353",
        "pdb": "cov",
        "chain": "E",
        "resnum": 488,
        "aa": "GLY",
        "name": "E488_GLY",
        "bonds": 1
      },
      {
        "id": "cov_1338",
        "pdb": "cov",
        "chain": "E",
        "resnum": 473,
        "aa": "ASN",
        "name": "E473_ASN",
        "bonds": 2
      },
      {
        "id": "cov2_713",
        "pdb": "cov2",
        "chain": "E",
        "resnum": 449,
        "aa": "TYR",
        "name": "E449_TYR",
        "bonds": 2
      },
      {
        "id": "cov2_681",
        "pdb": "cov2",
        "chain": "E",
        "resnum": 417,
        "aa": "LYS",
        "name": "E417_LYS",
        "bonds": 1
      },
      {
        "id": "cov2_717",
        "pdb": "cov2",
        "chain": "E",
        "resnum": 453,
        "aa": "TYR",
        "name": "E453_TYR",
        "bonds": 1
      },
      {
        "id": "cov2_751",
        "pdb": "cov2",
        "chain": "E",
        "resnum": 487,
        "aa": "ASN",
        "name": "E487_ASN",
        "bonds": 1
      },
      {
        "id": "cov2_757",
        "pdb": "cov2",
        "chain": "E",
        "resnum": 493,
        "aa": "GLN",
        "name": "E493_GLN",
        "bonds": 1
      },
      {
        "id": "cov2_762",
        "pdb": "cov2",
        "chain": "E",
        "resnum": 498,
        "aa": "GLN",
        "name": "E498_GLN",
        "bonds": 1
      },
      {
        "id": "cov2_764",
        "pdb": "cov2",
        "chain": "E",
        "resnum": 500,
        "aa": "THR",
        "name": "E500_THR",
        "bonds": 1
      },
      {
        "id": "cov2_766",
        "pdb": "cov2",
        "chain": "E",
        "resnum": 502,
        "aa": "GLY",
        "name": "E502_GLY",
        "bonds": 1
      },
      {
        "id": "cov2_11",
        "pdb": "cov2",
        "chain": "A",
        "resnum": 30,
        "aa": "ASP",
        "name": "A30_ASP",
        "bonds": 1
      },
      {
        "id": "cov2_19",
        "pdb": "cov2",
        "chain": "A",
        "resnum": 38,
        "aa": "ASP",
        "name": "A38_ASP",
        "bonds": 1
      },
      {
        "id": "cov2_15",
        "pdb": "cov2",
        "chain": "A",
        "resnum": 34,
        "aa": "HIS",
        "name": "A34_HIS",
        "bonds": 1
      },
      {
        "id": "cov2_64",
        "pdb": "cov2",
        "chain": "A",
        "resnum": 83,
        "aa": "TYR",
        "name": "A83_TYR",
        "bonds": 1
      },
      {
        "id": "cov2_5",
        "pdb": "cov2",
        "chain": "A",
        "resnum": 24,
        "aa": "GLN",
        "name": "A24_GLN",
        "bonds": 1
      },
      {
        "id": "cov2_12",
        "pdb": "cov2",
        "chain": "A",
        "resnum": 31,
        "aa": "LYS",
        "name": "A31_LYS",
        "bonds": 1
      },
      {
        "id": "cov2_22",
        "pdb": "cov2",
        "chain": "A",
        "resnum": 41,
        "aa": "TYR",
        "name": "A41_TYR",
        "bonds": 1
      },
      {
        "id": "cov2_334",
        "pdb": "cov2",
        "chain": "A",
        "resnum": 353,
        "aa": "LYS",
        "name": "A353_LYS",
        "bonds": 1
      },
      {
        "id": "cov2_23",
        "pdb": "cov2",
        "chain": "A",
        "resnum": 42,
        "aa": "GLN",
        "name": "A42_GLN",
        "bonds": 2
      }
    ],
    "links": [
      {
        "source": "cov_310",
        "target": "cov_1291",
        "strength": 1
      },
      {
        "source": "cov_23",
        "target": "cov_1301",
        "strength": 1
      },
      {
        "source": "cov_5",
        "target": "cov_1338",
        "strength": 1
      },
      {
        "source": "cov_64",
        "target": "cov_1338",
        "strength": 1
      },
      {
        "source": "cov_311",
        "target": "cov_1351",
        "strength": 1
      },
      {
        "source": "cov_22",
        "target": "cov_1351",
        "strength": 1
      },
      {
        "source": "cov_334",
        "target": "cov_1353",
        "strength": 1
      },
      {
        "source": "cov2_681",
        "target": "cov2_11",
        "strength": 1
      },
      {
        "source": "cov2_713",
        "target": "cov2_23",
        "strength": 1
      },
      {
        "source": "cov2_713",
        "target": "cov2_19",
        "strength": 1
      },
      {
        "source": "cov2_717",
        "target": "cov2_15",
        "strength": 1
      },
      {
        "source": "cov2_751",
        "target": "cov2_64",
        "strength": 1
      },
      {
        "source": "cov2_751",
        "target": "cov2_5",
        "strength": 1
      },
      {
        "source": "cov2_757",
        "target": "cov2_12",
        "strength": 1
      },
      {
        "source": "cov2_762",
        "target": "cov2_23",
        "strength": 1
      },
      {
        "source": "cov2_764",
        "target": "cov2_22",
        "strength": 1
      },
      {
        "source": "cov2_766",
        "target": "cov2_334",
        "strength": 1
      }
    ]
  }